agentic/__init__.py
agentic/agent/__init__.py
agentic/agent/agents.py
agentic/agent/base.py
agentic/agent/workflow.py
agentic/core/__init__.py
agentic/core/common_config.py
agentic/core/config.py
agentic/core/context.py
agentic/core/decorators.py
agentic/core/logging.py
agentic/core/paths.py
agentic/core/progress.py
agentic/core/run_workflow.py
agentic/core/typing.py
agentic/core/clients/chat_client.py
agentic/core/clients/coordinator_client.py
agentic/core/clients/grpc_channel.py
agentic/core/serialization/base.py
agentic/core/serialization/task.py
agentic/io/__init__.py
agentic/io/base/graphql_api.py
agentic/io/code/__init__.py
agentic/io/code/python.py
agentic/io/github/__init__.py
agentic/io/gmail/__init__.py
agentic/io/sh/__init__.py
agentic/io/sqlite/__init__.py
agentic/llm/__init__.py
agentic/llm/chat.py
agentic/llm/agentic_openai/__init__.py
agentic/llm/agentic_openai/config.py
agentic/llm/agentic_openai/util.py
agentic/proto/chat_pb2.py
agentic/proto/chat_pb2.pyi
agentic/proto/chat_pb2_grpc.py
agentic/proto/coordinator_pb2.py
agentic/proto/coordinator_pb2.pyi
agentic/proto/coordinator_pb2_grpc.py
agentic/proto/task_types_agent_pb2.py
agentic/proto/task_types_agent_pb2.pyi
agentic/proto/task_types_agent_pb2_grpc.py
agentic/proto/task_types_base_pb2.py
agentic/proto/task_types_base_pb2.pyi
agentic/proto/task_types_base_pb2_grpc.py
agentic/scripts/make_cli.py
agentic/scripts/run.py
agentic/util/__init__.py
agentic_py-0.1.3.dist-info/LICENSE
agentic_py-0.1.3.dist-info/METADATA
agentic_py-0.1.3.dist-info/WHEEL
agentic_py-0.1.3.dist-info/top_level.txt
agentic_py-0.1.3.dist-info/RECORD
